thinkcol_llm_client/__init__.py
thinkcol_llm_client/bedrock/clients.py
thinkcol_llm_client/bedrock/models.py
thinkcol_llm_client/bedrock/payloads.py
thinkcol_llm_client/chat_client.py
thinkcol_llm_client/constants.py
thinkcol_llm_client/openai_client.py
thinkcol_llm_client-0.1.3.dist-info/METADATA
thinkcol_llm_client-0.1.3.dist-info/WHEEL
thinkcol_llm_client-0.1.3.dist-info/RECORD
