Metadata-Version: 2.1
Name: thinkcol_llm_client
Version: 0.1.3
Summary: Package for calling llm clients asynchronously
Author: jedric01
Author-email: jedric@connect.ust.hk
Requires-Python: >=3.9,<4.0
Classifier: Programming Language :: Python :: 3
Classifier: Programming Language :: Python :: 3.9
Classifier: Programming Language :: Python :: 3.10
Classifier: Programming Language :: Python :: 3.11
Classifier: Programming Language :: Python :: 3.12
Requires-Dist: boto3 (>=1.34.68,<2.0.0)
Requires-Dist: openai (>=1.14.2,<2.0.0)
Requires-Dist: python-dotenv (>=1.0.1,<2.0.0)
